aws_profile_manager/__init__.py
aws_profile_manager/_version.py
aws_profile_manager/cli.py
aws_profile_manager/commands/__init__.py
aws_profile_manager/commands/profile-add.py
aws_profile_manager/commands/profile-current.py
aws_profile_manager/commands/profile-edit.py
aws_profile_manager/commands/profile-list.py
aws_profile_manager/commands/profile-remove.py
aws_profile_manager/commands/profile-switch.py
aws_profile_manager/commands/rotate-keys.py
aws_profile_manager/common/__init__.py
aws_profile_manager/common/common.py
aws_profile_manager/profile_add/__init__.py
aws_profile_manager/profile_add/add.py
aws_profile_manager/profile_edit/__init__.py
aws_profile_manager/profile_edit/edit.py
aws_profile_manager/profile_switch/__init__.py
aws_profile_manager/profile_switch/switch.py
aws_profile_manager/rotate_keys/__init__.py
aws_profile_manager/rotate_keys/rotate.py
aws_profile_manager/tests/__init__.py
aws_profile_manager/tests/common.py
aws_profile_manager/tests/switch.py
aws_profile_manager-0.7.3.dist-info/LICENSE
aws_profile_manager-0.7.3.dist-info/METADATA
aws_profile_manager-0.7.3.dist-info/WHEEL
aws_profile_manager-0.7.3.dist-info/entry_points.txt
aws_profile_manager-0.7.3.dist-info/top_level.txt
aws_profile_manager-0.7.3.dist-info/RECORD
