Metadata-Version: 2.1
Name: aws-profile-manager
Version: 0.7.3
Summary: This util allows you to manager your AWS profiles like add, remove, update and switch default AWS CLI profile
Home-page: https://github.com/99stealth/aws-profile-manager
Author: Roman Banakh
Author-email: banakh.ri@gmail.com
License: MIT
Classifier: License :: OSI Approved :: MIT License
Classifier: Programming Language :: Python :: 3
Classifier: Programming Language :: Python :: 3.5
Classifier: Programming Language :: Python :: 3.6
Classifier: Programming Language :: Python :: 3.7
Classifier: Programming Language :: Python :: 3.8
Classifier: Programming Language :: Python :: 3.9
Classifier: Programming Language :: Python :: 3.10
License-File: LICENSE
Requires-Dist: configparser
Requires-Dist: argparse
Requires-Dist: click
Requires-Dist: boto3
